klab_pytest_toolkit_webfixtures/__init__.py
klab_pytest_toolkit_webfixtures/api_client.py
klab_pytest_toolkit_webfixtures/core.py
klab_pytest_toolkit_webfixtures/plugin.py
klab_pytest_toolkit_webfixtures/validators.py
klab_pytest_toolkit_webfixtures/web_client.py
klab_pytest_toolkit_webfixtures-0.0.1.dist-info/METADATA
klab_pytest_toolkit_webfixtures-0.0.1.dist-info/WHEEL
klab_pytest_toolkit_webfixtures-0.0.1.dist-info/entry_points.txt
klab_pytest_toolkit_webfixtures-0.0.1.dist-info/RECORD
